pystrike/__init__.py
pystrike/charge.py
pystrike/exceptions.py
pystrike-0.5.2.dist-info/METADATA
pystrike-0.5.2.dist-info/RECORD
pystrike-0.5.2.dist-info/WHEEL
pystrike-0.5.2.dist-info/top_level.txt
test/__init__.py
test/test_charge.py
