Metadata-Version: 2.1
Name: pystrike
Version: 0.5.2
Summary: Python library for interacting with Acinq's Strike lightning network payment web service.
Home-page: https://github.com/JASchilz/pystrike
Author: Joseph Schilz
Author-email: joseph@schilz.org
License: UNKNOWN
Platform: UNKNOWN
Classifier: Programming Language :: Python :: 3
Classifier: License :: OSI Approved :: MIT License
Classifier: Operating System :: OS Independent
Classifier: Topic :: Software Development :: Libraries
